datasette_pins/__init__.py
datasette_pins/internal_migrations.py
datasette_pins/static/home/index.min.css
datasette_pins/static/home/index.min.js
datasette_pins/static/reorder_view/index.min.js
datasette_pins/templates/reorder_view.html
datasette_pins-0.1a6.dist-info/licenses/LICENSE
datasette_pins-0.1a6.dist-info/METADATA
datasette_pins-0.1a6.dist-info/WHEEL
datasette_pins-0.1a6.dist-info/entry_points.txt
datasette_pins-0.1a6.dist-info/top_level.txt
datasette_pins-0.1a6.dist-info/RECORD
