Metadata-Version: 2.4
Name: datasette-pins
Version: 0.1a6
Summary: Pin databases, tables, and other items to the Datasette homepage
Author: Alex Garcia
License-Expression: Apache-2.0
Project-URL: Homepage, https://github.com/datasette/datasette-pins
Project-URL: Changelog, https://github.com/datasette/datasette-pins/releases
Project-URL: Issues, https://github.com/datasette/datasette-pins/issues
Project-URL: CI, https://github.com/datasette/datasette-pins/actions
Classifier: Framework :: Datasette
Requires-Python: >=3.10
License-File: LICENSE
Requires-Dist: datasette>=1.0a21
Requires-Dist: sqlite-migrate>=0.1b0
Provides-Extra: test
Requires-Dist: pytest; extra == "test"
Requires-Dist: pytest-asyncio; extra == "test"
Requires-Dist: ruff; extra == "test"
Dynamic: license-file
